[
  {
    "id": 1,
    "title": "IA de Atendimento",
    "description": "Automatize suporte via WhatsApp.",
    "image": "assets/Carrosel/download.jpg",
    "slug": "ia-atendimento"
  },
  {
    "id": 2,
    "title": "Analisador de Documentos",
    "description": "Extrai e identifica informações automaticamente.",
    "image": "assets/Carrosel/images.jpg",
    "slug": "ia-documentos"
  },
  {
    "id": 3,
    "title": "Recomendador de Produtos",
    "description": "Sugestões inteligentes para seus clientes.",
    "image": "assets/Carrosel/robo.jpg",
    "slug": "ia-documentos"
  },
  {
    "id": 4,
    "title": "Detector de Qualidade",
    "description": "Verificação visual e tempo real.",
    "image": "assets/Carrosel/robots.jpg",
    "slug": "ia-documentos"
  }
]
